{
    "classes": [
        {
            "className": "PolarChartCategoryAxisAngular",
            "lineNumber": 23,
            "object": true,
            "qualifiedClassName": "PolarChartCategoryAxisAngular",
            "slots": [
                {
                    "access": "public",
                    "index": 0,
                    "name": "handleCategoriesChanged",
                    "returnType": "void"
                }
            ],
            "superClasses": [
                {
                    "access": "public",
                    "name": "PolarChartAxisAngular"
                }
            ]
        }
    ],
    "inputFile": "polarchartcategoryaxisangular_p.h",
    "outputRevision": 68
}
