{
    "classes": [
        {
            "className": "QChartView",
            "enums": [
                {
                    "isClass": false,
                    "isFlag": false,
                    "name": "RubberBand",
                    "values": [
                        "NoRubberBand",
                        "VerticalRubberBand",
                        "HorizontalRubberBand",
                        "RectangleRubberBand",
                        "ClickThroughRubberBand"
                    ]
                }
            ],
            "lineNumber": 21,
            "object": true,
            "qualifiedClassName": "QChartView",
            "superClasses": [
                {
                    "access": "public",
                    "name": "QGraphicsView"
                }
            ]
        }
    ],
    "inputFile": "qchartview.h",
    "outputRevision": 68
}
